{
  "story": [
    {
      "ID": 1,
      "Texture": 0,
      "BGM": "105",
      "SFX": "0",
      "Head_Image": 1066,
      "Head_Shark": 0,
      "Head_x": 340,
      "Head_y": 430,
      "Face_Image": 0,
      "Face_x": 0,
      "Face_y": 0,
      "D_right": false,
      "TurnImage": false,
      "Name": "？？？",
      "Black": false,
      "Aside": false,
      "AsideTime": 0.3,
      "Content": "嗯？真巧啊，又是你們。",
      "Content_x": 300,
      "Content_y": 50,
      "ShowTalkBackImage": true,
      "AllShark": false
    },
    {
      "ID": 2,
      "Texture": 0,
      "BGM": "0",
      "SFX": "0",
      "Head_Image": 146,
      "Head_Shark": 1,
      "Head_x": 840,
      "Head_y": 320,
      "Face_Image": 5,
      "Face_x": 861,
      "Face_y": 515,
      "D_right": true,
      "TurnImage": true,
      "Name": "極品元",
      "Black": false,
      "Aside": false,
      "AsideTime": 0.3,
      "Content": "喂，你把小品怎麼樣了？！",
      "Content_x": 300,
      "Content_y": 50,
      "ShowTalkBackImage": true,
      "AllShark": false
    },
    {
      "ID": 3,
      "Texture": 0,
      "BGM": "0",
      "SFX": "0",
      "Head_Image": 1066,
      "Head_Shark": 0,
      "Head_x": 340,
      "Head_y": 430,
      "Face_Image": 0,
      "Face_x": 0,
      "Face_y": 0,
      "D_right": false,
      "TurnImage": false,
      "Name": "？？？",
      "Black": false,
      "Aside": false,
      "AsideTime": 0.3,
      "Content": "小品？",
      "Content_x": 300,
      "Content_y": 50,
      "ShowTalkBackImage": true,
      "AllShark": false
    },
    {
      "ID": 4,
      "Texture": 0,
      "BGM": "0",
      "SFX": "0",
      "Head_Image": 1066,
      "Head_Shark": 0,
      "Head_x": 340,
      "Head_y": 430,
      "Face_Image": 0,
      "Face_x": 0,
      "Face_y": 0,
      "D_right": false,
      "TurnImage": false,
      "Name": "？？？",
      "Black": false,
      "Aside": false,
      "AsideTime": 0.3,
      "Content": "哦，你說四百八十號，它很好，我剛準備將它送還給師傅。",
      "Content_x": 300,
      "Content_y": 50,
      "ShowTalkBackImage": true,
      "AllShark": false
    },
    {
      "ID": 5,
      "Texture": 0,
      "BGM": "0",
      "SFX": "0",
      "Head_Image": 146,
      "Head_Shark": 1,
      "Head_x": 840,
      "Head_y": 320,
      "Face_Image": 5,
      "Face_x": 861,
      "Face_y": 515,
      "D_right": true,
      "TurnImage": true,
      "Name": "極品元",
      "Black": false,
      "Aside": false,
      "AsideTime": 0.3,
      "Content": "什麼四百八十號，把她還給我！",
      "Content_x": 300,
      "Content_y": 50,
      "ShowTalkBackImage": true,
      "AllShark": false
    },
    {
      "ID": 6,
      "Texture": 0,
      "BGM": "0",
      "SFX": "0",
      "Head_Image": 1066,
      "Head_Shark": 0,
      "Head_x": 340,
      "Head_y": 430,
      "Face_Image": 0,
      "Face_x": 0,
      "Face_y": 0,
      "D_right": false,
      "TurnImage": false,
      "Name": "？？？",
      "Black": false,
      "Aside": false,
      "AsideTime": 0.3,
      "Content": "小子，先擔心一下自己吧。",
      "Content_x": 300,
      "Content_y": 50,
      "ShowTalkBackImage": true,
      "AllShark": false
    },
    {
      "ID": 7,
      "Texture": 0,
      "BGM": "0",
      "SFX": "0",
      "Head_Image": 1056,
      "Head_Shark": 0,
      "Head_x": 350,
      "Head_y": 270,
      "Face_Image": 0,
      "Face_x": 0,
      "Face_y": 0,
      "D_right": false,
      "TurnImage": false,
      "Name": "？？？",
      "Black": false,
      "Aside": false,
      "AsideTime": 0.3,
      "Content": "吼！！",
      "Content_x": 300,
      "Content_y": 50,
      "ShowTalkBackImage": true,
      "AllShark": true
    }
  ]
}