{
  "story": [
    {
      "ID": 1,
      "Texture": 0,
      "BGM": "",
      "SFX": "0",
      "Head_Image": 0,
      "Head_Shark": 0,
      "Head_x": 0,
      "Head_y": 0,
      "Face_Image": 0,
      "Face_x": 0,
      "Face_y": 0,
      "D_right": true,
      "TurnImage": false,
      "Name": " ",
      "Black": true,
      "Aside": true,
      "AsideTime": 1,
      "Content": "",
      "Content_x": 150,
      "Content_y": 330,
      "ShowTalkBackImage": false,
      "AllShark": false
    },
    {
      "ID": 2,
      "Texture": 0,
      "BGM": "",
      "SFX": "0",
      "Head_Image": 0,
      "Head_Shark": 0,
      "Head_x": 0,
      "Head_y": 0,
      "Face_Image": 0,
      "Face_x": 0,
      "Face_y": 0,
      "D_right": true,
      "TurnImage": false,
      "Name": " ",
      "Black": true,
      "Aside": true,
      "AsideTime": 3,
      "Content": "為了那個人，我定要覓到此地。",
      "Content_x": 150,
      "Content_y": 330,
      "ShowTalkBackImage": false,
      "AllShark": false
    }
  ]
}